{
  "date": "2026-07-14",
  "npcs": [
    {
      "npc_name": "아즈사",
      "shop_id": 2100001,
      "items": [
        {
          "grid_id": 1,
          "pool_id": 2100001,
          "pool_index": 100,
          "item_id": 5013007,
          "item_name": "간장 계란밥",
          "nyang_coin_reward": 200
        },
        {
          "grid_id": 2,
          "pool_id": 2100003,
          "pool_index": 303,
          "item_id": 5012004,
          "item_name": "후추",
          "nyang_coin_reward": 350
        }
      ]
    },
    {
      "npc_name": "아야",
      "shop_id": 2100002,
      "items": [
        {
          "grid_id": 1,
          "pool_id": 2100002,
          "pool_index": 368,
          "item_id": 5013076,
          "item_name": "매콤 가오리찜",
          "nyang_coin_reward": 800
        },
        {
          "grid_id": 2,
          "pool_id": 2100002,
          "pool_index": 218,
          "item_id": 5013024,
          "item_name": "마늘 석화구이",
          "nyang_coin_reward": 600
        },
        {
          "grid_id": 3,
          "pool_id": 2100002,
          "pool_index": 359,
          "item_id": 5013067,
          "item_name": "해산물 크림수프",
          "nyang_coin_reward": 800
        }
      ]
    },
    {
      "npc_name": "리처드",
      "shop_id": 2200001,
      "items": [
        {
          "grid_id": 1,
          "pool_id": 2200001,
          "pool_index": 213,
          "item_id": 5033014,
          "item_name": "바지 샘플",
          "nyang_coin_reward": 800
        },
        {
          "grid_id": 2,
          "pool_id": 2200001,
          "pool_index": 210,
          "item_id": 5033011,
          "item_name": "손목 커버 샘플",
          "nyang_coin_reward": 800
        },
        {
          "grid_id": 3,
          "pool_id": 2200001,
          "pool_index": 206,
          "item_id": 5033007,
          "item_name": "넥타이 샘플",
          "nyang_coin_reward": 800
        }
      ]
    }
  ],
  "live_meta": {
    "verify_status": 1,
    "login_status": 1,
    "main_status": 1,
    "change_scene_status": 1,
    "change_scene_id": 1
  }
}