{
  "date": "2026-06-27",
  "npcs": [
    {
      "npc_name": "아즈사",
      "shop_id": 2100001,
      "items": [
        {
          "grid_id": 1,
          "pool_id": 2100001,
          "pool_index": 104,
          "item_id": 5013019,
          "item_name": "계란 볶음밥",
          "nyang_coin_reward": 200
        },
        {
          "grid_id": 2,
          "pool_id": 2100003,
          "pool_index": 105,
          "item_id": 5012006,
          "item_name": "요리용 맛술",
          "nyang_coin_reward": 150
        }
      ]
    },
    {
      "npc_name": "아야",
      "shop_id": 2100002,
      "items": [
        {
          "grid_id": 1,
          "pool_id": 2100002,
          "pool_index": 359,
          "item_id": 5013067,
          "item_name": "해산물 크림수프",
          "nyang_coin_reward": 800
        },
        {
          "grid_id": 2,
          "pool_id": 2100002,
          "pool_index": 231,
          "item_id": 5013039,
          "item_name": "진한 골설어 수프",
          "nyang_coin_reward": 600
        },
        {
          "grid_id": 3,
          "pool_id": 2100002,
          "pool_index": 217,
          "item_id": 5013022,
          "item_name": "부드러운 연어회",
          "nyang_coin_reward": 600
        }
      ]
    },
    {
      "npc_name": "리처드",
      "shop_id": 2200001,
      "items": [
        {
          "grid_id": 1,
          "pool_id": 2200001,
          "pool_index": 205,
          "item_id": 5033006,
          "item_name": "외투 샘플",
          "nyang_coin_reward": 800
        },
        {
          "grid_id": 2,
          "pool_id": 2200001,
          "pool_index": 114,
          "item_id": 5033015,
          "item_name": "치마 샘플",
          "nyang_coin_reward": 600
        },
        {
          "grid_id": 3,
          "pool_id": 2200001,
          "pool_index": 111,
          "item_id": 5033012,
          "item_name": "팔찌 샘플",
          "nyang_coin_reward": 600
        }
      ]
    }
  ],
  "live_meta": {
    "verify_status": 1,
    "login_status": 1,
    "main_status": 1,
    "change_scene_status": 1,
    "change_scene_id": 1
  }
}